.gitignore
CHANGELOG.md
LICENSE
MANIFEST.in
README.rst
requirements.txt
setup.py
pylint_pmd/__init__.py
pylint_pmd.egg-info/PKG-INFO
pylint_pmd.egg-info/SOURCES.txt
pylint_pmd.egg-info/dependency_links.txt
pylint_pmd.egg-info/not-zip-safe
pylint_pmd.egg-info/requires.txt
pylint_pmd.egg-info/top_level.txt