Metadata-Version: 1.1
Name: pylint-pmd
Version: 0.0.1
Summary: Generate PMD compatible reports for pylint
Home-page: https://github.com/diasjorge/pylint-pmd
Author: Jorge Dias
Author-email: jorge@mrdias.com
License: FreeBSD License
Keywords: Pylint,PMD
Platform: UNKNOWN
Classifier: Development Status :: 3 - Alpha
Classifier: Environment :: Console
Classifier: Intended Audience :: Developers
Classifier: License :: OSI Approved :: BSD License
Classifier: Natural Language :: English
Classifier: Programming Language :: Python :: 2.7
Classifier: Topic :: Utilities
